{
    "id": "20170526_153710_0e0e",
    "type": "Feature",
    "geometry": {
        "type": "Polygon",
        "coordinates": [
            [
                [
                    -84.7587,
                    31.188475479855768
                ],
                [
                    -84.7652,
                    31.189663269522907
                ],
                [
                    -84.7652,
                    31.1932
                ],
                [
                    -84.7587,
                    31.1932
                ],
                [
                    -84.7587,
                    31.188475479855768
                ]
            ]
        ]
    },
    "properties": {
        "acquired": "2017-05-26T15:37:10.231554Z",
        "anomalous_pixels": 0.01,
        "clear_confidence_percent": 95,
        "clear_percent": 100,
        "cloud_cover": 0.0,
        "cloud_percent": 0,
        "ground_control": true,
        "gsd": 3.9,
        "heavy_haze_percent": 0,
        "instrument": "PS2",
        "item_type": "PSScene",
        "light_haze_percent": 0,
        "pixel_resolution": 3,
        "provider": "planetscope",
        "published": "2021-02-09T12:48:46Z",
        "publishing_stage": "finalized",
        "quality_category": "standard",
        "satellite_azimuth": 5,
        "satellite_id": "0e0e",
        "shadow_percent": 0,
        "snow_ice_percent": 0,
        "strip_id": "520389",
        "sun_azimuth": 103.4,
        "sun_elevation": 61.7,
        "updated": "2024-04-19T12:51:49Z",
        "view_angle": 0.2,
        "visible_confidence_percent": 95,
        "visible_percent": 100
    }
}